rest_framework_jet/__init__.py
rest_framework_jet/admin.py
rest_framework_jet/apps.py
rest_framework_jet/authentication.py
rest_framework_jet/models.py
rest_framework_jet/tests.py
rest_framework_jet/views.py
rest_framework_jet/migrations/__init__.py
django_rest_framework_jet-0.0.6.dist-info/LICENSE
django_rest_framework_jet-0.0.6.dist-info/METADATA
django_rest_framework_jet-0.0.6.dist-info/WHEEL
django_rest_framework_jet-0.0.6.dist-info/top_level.txt
django_rest_framework_jet-0.0.6.dist-info/RECORD
