Metadata-Version: 2.1
Name: django-rest-framework-jet
Version: 0.0.6
Summary: JET - Django APP
Home-page: https://github.com/FR98/django-rest-framework-jet
Author: Francisco Rosal
Author-email: ros18676@uvg.edu.gt
License: UNKNOWN
Platform: UNKNOWN
Classifier: Programming Language :: Python :: 3
Classifier: License :: OSI Approved :: MIT License
Classifier: Operating System :: OS Independent
Classifier: Environment :: Web Environment
Classifier: Framework :: Django
Classifier: Intended Audience :: Developers
Classifier: Programming Language :: Python
Classifier: Programming Language :: Python :: 3
Classifier: Programming Language :: Python :: 3 :: Only
Classifier: Programming Language :: Python :: 3.6
Classifier: Programming Language :: Python :: 3.7
Classifier: Programming Language :: Python :: 3.8
Classifier: Topic :: Internet :: WWW/HTTP
Classifier: Topic :: Internet :: WWW/HTTP :: Dynamic Content
Requires-Python: >=3.6
Requires-Dist: djangorestframework (==3.11.0)
Requires-Dist: json-encrypted-token (==0.0.6)
